<?xml version = '1.0' encoding = 'UTF-8'?>
<Diagram class="oracle.dbtools.crest.swingui.relational.DPVRelational" name="Relational_1" id="202F2004-A39C-5428-6ED3-A53816135AA5">
<createdBy>yuehan</createdBy>
<modifiedBy>yuehan</modifiedBy>
<createdTime>2020-04-06 19:38:56 UTC</createdTime>
<autoRoute>false</autoRoute>
<boxInbox>true</boxInbox>
<showLegend>false</showLegend>
<showLabels>false</showLabels>
<showRelAttributes>false</showRelAttributes>
<gridEnabled>false</gridEnabled>
<showGrid>false</showGrid>
<diagramColor>-1</diagramColor>
<display>false</display>
<notation>1</notation>
<objectViews>
<OView class="oracle.dbtools.crest.swingui.relational.TVTable" oid="14027D5A-C205-94FE-DA62-B627EF478F15" otype="Table" vid="624EE800-A217-64C1-D8F7-F0B73E11B261">
<hideElementsInCurrentOnly>false</hideElementsInCurrentOnly>
<bounds x="674" y="477" width="244" height="112"/>
</OView>
<OView class="oracle.dbtools.crest.swingui.relational.TVTable" oid="22ADA15F-D503-7566-BDEB-541A83A6F04D" otype="Table" vid="E1D85850-BC25-EED6-4879-1731A6BC6A4D">
<hideElementsInCurrentOnly>false</hideElementsInCurrentOnly>
<bounds x="5" y="11" width="331" height="219"/>
</OView>
<OView class="oracle.dbtools.crest.swingui.relational.TVTable" oid="274092E5-1756-B2FC-1D01-B9EAA99EE094" otype="Table" vid="B14E6368-E63E-CEA5-796B-8551A0652C7D">
<hideElementsInCurrentOnly>false</hideElementsInCurrentOnly>
<bounds x="5" y="484" width="209" height="203"/>
</OView>
<OView class="oracle.dbtools.crest.swingui.relational.TVTable" oid="4FB99452-2CE5-0F55-75B2-32595F5C5223" otype="Table" vid="7A83070A-BDAB-E81C-172A-0565DCB8D47D">
<hideElementsInCurrentOnly>false</hideElementsInCurrentOnly>
<bounds x="158" y="284" width="277" height="138"/>
</OView>
<OView class="oracle.dbtools.crest.swingui.relational.TVTable" oid="5B719625-54FB-CF54-778F-FCE4E00DEE3B" otype="Table" vid="A0DE84E1-A700-2B82-2277-19A0F2BD2CBB">
<hideElementsInCurrentOnly>false</hideElementsInCurrentOnly>
<bounds x="302" y="668" width="229" height="141"/>
</OView>
<OView class="oracle.dbtools.crest.swingui.relational.TVTable" oid="9EEE4BFE-E111-8FCF-EFFF-A5D2844FACE2" otype="Table" vid="D55ED5E6-8396-B688-0D3B-4198488F90FC">
<hideElementsInCurrentOnly>false</hideElementsInCurrentOnly>
<bounds x="614" y="253" width="226" height="160"/>
</OView>
<OView class="oracle.dbtools.crest.swingui.relational.TVTable" oid="B0EDA6BC-4F44-DC18-0E7E-8FC11EB16257" otype="Table" vid="3C26D1A7-8C88-1D6D-E6B0-665F430AB7F2">
<hideElementsInCurrentOnly>false</hideElementsInCurrentOnly>
<bounds x="297" y="488" width="236" height="130"/>
</OView>
<OView class="oracle.dbtools.crest.swingui.relational.TVTable" oid="ED43680A-776F-7883-C71C-8B5F33EC86D4" otype="Table" vid="BD1B182E-F992-551E-B5D0-C4C7143CA471">
<hideElementsInCurrentOnly>false</hideElementsInCurrentOnly>
<bounds x="710" y="676" width="213" height="113"/>
</OView>
<OView class="oracle.dbtools.crest.swingui.relational.TVTable" oid="ED5A3439-C396-4C41-A7FF-06540914DE4F" otype="Table" vid="3E69AB70-B805-5D13-6C94-4F2C904D4FC8">
<hideElementsInCurrentOnly>false</hideElementsInCurrentOnly>
<bounds x="1001" y="50" width="225" height="138"/>
</OView>
<OView class="oracle.dbtools.crest.swingui.relational.TVTable" oid="F78F1F3A-FD6E-BEE0-7AC0-7E829B87BAB5" otype="Table" vid="EE3EAE64-9CDD-43C3-E8E6-62767DD15ABE">
<hideElementsInCurrentOnly>false</hideElementsInCurrentOnly>
<bounds x="399" y="51" width="229" height="133"/>
</OView>
<OView class="oracle.dbtools.crest.swingui.relational.TVTable" oid="F7C5FA03-B3F4-2E57-B4A1-158717167DAD" otype="Table" vid="A18899EC-4A1B-E084-C70E-50F05A6FBE40">
<hideElementsInCurrentOnly>false</hideElementsInCurrentOnly>
<bounds x="693" y="48" width="227" height="142"/>
</OView>
</objectViews>
<connectors>
<Connector class="oracle.dbtools.crest.swingui.relational.TVFKRelation" oid="4790E6FE-DA75-B641-3591-D58F4BDE88E3" otype="FKIndexAssociation" vid_source="7A83070A-BDAB-E81C-172A-0565DCB8D47D" vid_target="3C26D1A7-8C88-1D6D-E6B0-665F430AB7F2">
<hideElementsInCurrentOnly>false</hideElementsInCurrentOnly>
<backgroundColor>-16777216</backgroundColor>
<lineWidth>1</lineWidth>
<points>
<point x="366" y="422"/>
<point x="366" y="488"/>
</points>
</Connector>
<Connector class="oracle.dbtools.crest.swingui.relational.TVFKRelation" oid="603D0284-7E80-02DB-20F5-965704935067" otype="FKIndexAssociation" vid_source="A18899EC-4A1B-E084-C70E-50F05A6FBE40" vid_target="3E69AB70-B805-5D13-6C94-4F2C904D4FC8">
<hideElementsInCurrentOnly>false</hideElementsInCurrentOnly>
<backgroundColor>-16777216</backgroundColor>
<lineWidth>1</lineWidth>
<points>
<point x="920" y="119"/>
<point x="1001" y="119"/>
</points>
</Connector>
<Connector class="oracle.dbtools.crest.swingui.relational.TVFKRelation" oid="682921FC-5F3B-FE17-4BEB-A9558C2FB7C9" otype="FKIndexAssociation" vid_source="E1D85850-BC25-EED6-4879-1731A6BC6A4D" vid_target="7A83070A-BDAB-E81C-172A-0565DCB8D47D">
<hideElementsInCurrentOnly>false</hideElementsInCurrentOnly>
<backgroundColor>-16777216</backgroundColor>
<lineWidth>1</lineWidth>
<points>
<point x="247" y="230"/>
<point x="247" y="284"/>
</points>
</Connector>
<Connector class="oracle.dbtools.crest.swingui.relational.TVFKRelation" oid="7A432F82-253E-D8F0-C9DE-A0C061ED5B8E" otype="FKIndexAssociation" vid_source="EE3EAE64-9CDD-43C3-E8E6-62767DD15ABE" vid_target="A18899EC-4A1B-E084-C70E-50F05A6FBE40">
<hideElementsInCurrentOnly>false</hideElementsInCurrentOnly>
<backgroundColor>-16777216</backgroundColor>
<lineWidth>1</lineWidth>
<points>
<point x="628" y="117"/>
<point x="693" y="117"/>
</points>
</Connector>
<Connector class="oracle.dbtools.crest.swingui.relational.TVFKRelation" oid="A21E04C4-A7FB-3551-650C-3EF351EDE891" otype="FKIndexAssociation" vid_source="E1D85850-BC25-EED6-4879-1731A6BC6A4D" vid_target="EE3EAE64-9CDD-43C3-E8E6-62767DD15ABE">
<hideElementsInCurrentOnly>false</hideElementsInCurrentOnly>
<backgroundColor>-16777216</backgroundColor>
<lineWidth>1</lineWidth>
<points>
<point x="336" y="117"/>
<point x="399" y="117"/>
</points>
</Connector>
<Connector class="oracle.dbtools.crest.swingui.relational.TVFKRelation" oid="A49DB1CB-F3D8-AF9F-A3FF-909A49D0EC7A" otype="FKIndexAssociation" vid_source="EE3EAE64-9CDD-43C3-E8E6-62767DD15ABE" vid_target="D55ED5E6-8396-B688-0D3B-4198488F90FC">
<hideElementsInCurrentOnly>false</hideElementsInCurrentOnly>
<backgroundColor>-16777216</backgroundColor>
<lineWidth>1</lineWidth>
<points>
<point x="621" y="184"/>
<point x="621" y="253"/>
</points>
</Connector>
<Connector class="oracle.dbtools.crest.swingui.relational.TVFKRelation" oid="A5844A94-57AC-8C76-4DC1-0168562C1FFF" otype="FKIndexAssociation" vid_source="7A83070A-BDAB-E81C-172A-0565DCB8D47D" vid_target="B14E6368-E63E-CEA5-796B-8551A0652C7D">
<hideElementsInCurrentOnly>false</hideElementsInCurrentOnly>
<backgroundColor>-16777216</backgroundColor>
<lineWidth>1</lineWidth>
<points>
<point x="186" y="422"/>
<point x="186" y="484"/>
</points>
</Connector>
<Connector class="oracle.dbtools.crest.swingui.relational.TVFKRelation" oid="B44B328A-EA98-3C74-0D7E-7E95815EAC87" otype="FKIndexAssociation" vid_source="D55ED5E6-8396-B688-0D3B-4198488F90FC" vid_target="624EE800-A217-64C1-D8F7-F0B73E11B261">
<hideElementsInCurrentOnly>false</hideElementsInCurrentOnly>
<backgroundColor>-16777216</backgroundColor>
<lineWidth>1</lineWidth>
<points>
<point x="757" y="413"/>
<point x="757" y="477"/>
</points>
</Connector>
<Connector class="oracle.dbtools.crest.swingui.relational.TVFKRelation" oid="B47AADCE-15C7-EECA-3767-DFF0D4C2104E" otype="FKIndexAssociation" vid_source="BD1B182E-F992-551E-B5D0-C4C7143CA471" vid_target="624EE800-A217-64C1-D8F7-F0B73E11B261">
<hideElementsInCurrentOnly>false</hideElementsInCurrentOnly>
<backgroundColor>-16777216</backgroundColor>
<lineWidth>1</lineWidth>
<points>
<point x="814" y="676"/>
<point x="814" y="589"/>
</points>
</Connector>
<Connector class="oracle.dbtools.crest.swingui.relational.TVFKRelation" oid="BA751848-75B4-5003-8232-13D54F10D94E" otype="FKIndexAssociation" vid_source="3C26D1A7-8C88-1D6D-E6B0-665F430AB7F2" vid_target="A0DE84E1-A700-2B82-2277-19A0F2BD2CBB">
<hideElementsInCurrentOnly>false</hideElementsInCurrentOnly>
<backgroundColor>-16777216</backgroundColor>
<lineWidth>1</lineWidth>
<points>
<point x="416" y="618"/>
<point x="416" y="668"/>
</points>
</Connector>
</connectors>
<arcs>
<Arc class="oracle.dbtools.crest.swingui.relational.TVFKArc" oid="62E66B2C-F8D9-3B2E-CED8-33610D3FF376" otype="FKArc" vid="A603155C-2358-F5D9-4E35-2DEB84264274">
<hideElementsInCurrentOnly>false</hideElementsInCurrentOnly>
<bounds x="-15" y="-9" width="371" height="259"/>
</Arc>
</arcs>
</Diagram>
